{
  "1": [
    {
      "images": "https://cdna.lystit.com/cms/YIF_Banner_Desktop_6dfca0bc4a.jpg"
    },
    {
      "images": "https://cdna.lystit.com/cms/EN_Default_460f2da2ac.png"
    }
  ],
  "2":[
    {
      "images": "https://cdna.lystit.com/cms/7ec30147_3528_4e96_a650_57ef56b128b0_5904e59d33.png"
    },
    {
      "images": "https://cdna.lystit.com/cms/1041ba80_6450_45cb_a792_ee2e385ce278_c2537aebbc.png"
    },
    {
      "images": "https://cdna.lystit.com/cms/51758163_6a58_4e6d_bd8f_dcdb581ddf4f_92d2c86b06.png"
    },
    {
      "images": "https://cdna.lystit.com/cms/e72b0702_d849_4832_a19d_88d0d0302a66_794aecff7f.png"
    },
    {
      "images": "https://cdna.lystit.com/cms/600x600_Affiliate_Prada_Holiday_BU_1_1_e41fdd0245.jpg"
    }
  ],
  "3":[
    {
      "images": "https://cdna.lystit.com/cms/Top_Lyst5th_U_Sand_IT_600x600_s_594ad2e245.jpg"
    },
    {
      "images": "https://cdna.lystit.com/cms/EA_7_Gift_Finder_4f3e2522b6.jpg"
    },
    {
      "images": "https://cdna.lystit.com/cms/HP_Top_Lyst_Banner_600x600_6bb8c2a582.jpg"
    },
    {
      "images": "https://cdna.lystit.com/cms/balenciaga_b4eec10d67.jpg"
    },
    {
      "images": "https://cdna.lystit.com/cms/vivienne_westwood_f7d712c58e.jpg"
    }
  ],
  "4":[
    {
      "images": "https://cdna.lystit.com/cms/hoka_one_one_7c61e26c5a.jpg"
    },
    {
      "images": "https://cdna.lystit.com/cms/burberry_6d39746bc8.jpg"
    },
    {
      "images": "https://cdna.lystit.com/cms/fendi_cb9b2391df.png"
    },
    {
      "images": "https://cdna.lystit.com/cms/alexander_mcqueen_baedc5140b.jpg"
    },
    {
      "images": "https://cdna.lystit.com/cms/golden_goose_59e4b8afbb.jpg"
    }
  ],
    "5":[
    {
      "images": "https://cdna.lystit.com/cms/tory_burch_c2694d7614.jpg"
    },
    {
      "images": "https://cdna.lystit.com/cms/marc_jacobs_29e9988630.jpg"
    },
    {
      "images": "https://cdna.lystit.com/cms/moncler_627804ea66.jpeg"
    },
    {
      "images": "https://cdna.lystit.com/cms/ferragamo_belt_6f771dc38c.jpg"
    },
    {
      "images": "https://cdna.lystit.com/cms/mcqueen_sneakers_8bed6ead41.jpg"
    }
  ],
  "6":[
    {
      "images": "https://cdna.lystit.com/cms/gucci_scarf_fe36f0efcf.jpg"
    },
    {
      "images": "https://cdna.lystit.com/cms/canada_goose_jacket_8ef1b21a01.jpg"
    },
    {
      "images": "https://cdna.lystit.com/cms/mou_boots_b752d8b2d3.jpg"
    },
    {
      "images": "https://cdna.lystit.com/cms/coach_boots_501890e9f6.jpg"
    },
    {
      "images": "https://cdna.lystit.com/cms/moncler_jacket_2d491a95dc.jpg"
    }
  ],
  "7":[
    {
      "images": "https://cdna.lystit.com/cms/gucci_wallet_efb3e00367.jpg"
    },
    {
      "images": "https://cdna.lystit.com/cms/mackage_coat_c28797a0bf.jpg"
    },
    {
      "images": "https://cdna.lystit.com/cms/gucci_boots_b1ff8d0345.jpg"
    },
    {
      "images": "https://cdna.lystit.com/cms/prada_boots_6233e75fa8.jpg"
    },
    {
      "images": "https://cdna.lystit.com/cms/burberry_shirt_bfcb721a9f.jpg"
    },
    {
      "images": "https://cdna.lystit.com/cms/acne_scarf_962909ccdd.jpg"
    },
    {
      "images": "https://cdna.lystit.com/cms/mugler_jeans_23663c939e.jpg"
    },
    {
      "images": "https://cdna.lystit.com/480/480/r/cms/9454be62_615f_43d8_8c67_3e2483f5f261_49a452e8e7.png"
    }
  ]
}